README.rst
ldif3.py
setup.cfg
setup.py
ldif3.egg-info/PKG-INFO
ldif3.egg-info/SOURCES.txt
ldif3.egg-info/dependency_links.txt
ldif3.egg-info/top_level.txt