Metadata-Version: 1.1
Name: ldif3
Version: 3.0.1
Summary: generate and parse LDIF data (see RFC 2849).
Home-page: https://github.com/xi/ldif3
Author: Tobias Bengfort
Author-email: tobias.bengfort@posteo.de
License: BSD
Platform: UNKNOWN
Classifier: Development Status :: 4 - Beta
Classifier: Operating System :: OS Independent
Classifier: Programming Language :: Python
Classifier: License :: OSI Approved :: BSD License
Classifier: Intended Audience :: Developers
Classifier: Topic :: System :: Systems Administration :: Authentication/Directory :: LDAP
